edge_tpu_silva/__init__.py
edge_tpu_silva/__main__.py
edge_tpu_silva/deps/__init__.py
edge_tpu_silva/deps/check.py
edge_tpu_silva/deps/setup_comands.py
edge_tpu_silva/silva/__init__.py
edge_tpu_silva/silva/silva_classify.py
edge_tpu_silva/silva/silva_detect.py
edge_tpu_silva/silva/silva_segment.py
edge_tpu_silva-1.0.5.dist-info/METADATA
edge_tpu_silva-1.0.5.dist-info/WHEEL
edge_tpu_silva-1.0.5.dist-info/entry_points.txt
edge_tpu_silva-1.0.5.dist-info/top_level.txt
edge_tpu_silva-1.0.5.dist-info/RECORD
