Metadata-Version: 2.1
Name: edge-tpu-silva
Version: 1.0.5
Summary: UNKNOWN
Home-page: UNKNOWN
License: UNKNOWN
Platform: UNKNOWN
Requires-Python: >=3.6, <3.10
Requires-Dist: opencv-python
Requires-Dist: ultralytics
